yaml_helpers/EmbeddingYAML.py
yaml_helpers/SummaryYAML.py
yaml_helpers/config.py
yaml_helpers/utils.py
yaml_helpers-0.0.42.dist-info/METADATA
yaml_helpers-0.0.42.dist-info/WHEEL
yaml_helpers-0.0.42.dist-info/top_level.txt
yaml_helpers-0.0.42.dist-info/RECORD
