Metadata-Version: 2.1
Name: yaml_helpers
Version: 0.0.42
Summary: yaml helpers package
Author-email: Sanjer <sanjer@comm-it.com>
Classifier: Programming Language :: Python :: 3
Classifier: License :: OSI Approved :: MIT License
Classifier: Operating System :: OS Independent
Requires-Python: >=3.9
